{
  "countries": {
    "by_alpha2": {
      "AF": "Afghanistan",
      "AX": "Åland Islands",
      "AL": "Albania",
      "DZ": "Algeria",
      "AS": "American Samoa",
      "AD": "Andorra",
      "AO": "Angola",
      "AI": "Anguilla",
      "AQ": "Antarctica",
      "AG": "Antigua And Barbuda",
      "AR": "Argentina",
      "AM": "Armenia",
      "AW": "Aruba",
      "AU": "Australia",
      "AT": "Austria",
      "AZ": "Azerbaijan",
      "BS": "Bahamas",
      "BH": "Bahrain",
      "BD": "Bangladesh",
      "BB": "Barbados",
      "BY": "Belarus",
      "BE": "Belgium",
      "BZ": "Belize",
      "BJ": "Benin",
      "BM": "Bermuda",
      "BT": "Bhutan",
      "BO": "Bolivia, Plurinational State Of",
      "BA": "Bosnia And Herzegovina",
      "BW": "Botswana",
      "BV": "Bouvet Island",
      "BR": "Brazil",
      "IO": "British Indian Ocean Territory",
      "BN": "Brunei Darussalam",
      "BG": "Bulgaria",
      "BF": "Burkina Faso",
      "BI": "Burundi",
      "KH": "Cambodia",
      "CM": "Cameroon",
      "CA": "Canada",
      "CV": "Cape Verde",
      "KY": "Cayman Islands",
      "CF": "Central African Republic",
      "TD": "Chad",
      "CL": "Chile",
      "CN": "China",
      "CX": "Christmas Island",
      "CC": "Cocos (keeling) Islands",
      "CO": "Colombia",
      "KM": "Comoros",
      "CG": "Congo",
      "CD": "Congo, The Democratic Republic Of The",
      "CK": "Cook Islands",
      "CR": "Costa Rica",
      "CI": "Côte D'ivoire",
      "HR": "Croatia",
      "CU": "Cuba",
      "CY": "Cyprus",
      "CZ": "Czech Republic",
      "DK": "Denmark",
      "DJ": "Djibouti",
      "DM": "Dominica",
      "DO": "Dominican Republic",
      "EC": "Ecuador",
      "EG": "Egypt",
      "SV": "El Salvador",
      "GQ": "Equatorial Guinea",
      "ER": "Eritrea",
      "EE": "Estonia",
      "ET": "Ethiopia",
      "FK": "Falkland Islands (malvinas)",
      "FO": "Faroe Islands",
      "FJ": "Fiji",
      "FI": "Finland",
      "FR": "France",
      "GF": "French Guiana",
      "PF": "French Polynesia",
      "TF": "French Southern Territories",
      "GA": "Gabon",
      "GM": "Gambia",
      "GE": "Georgia",
      "DE": "Germany",
      "GH": "Ghana",
      "GI": "Gibraltar",
      "GR": "Greece",
      "GL": "Greenland",
      "GD": "Grenada",
      "GP": "Guadeloupe",
      "GU": "Guam",
      "GT": "Guatemala",
      "GG": "Guernsey",
      "GN": "Guinea",
      "GW": "Guinea-bissau",
      "GY": "Guyana",
      "HT": "Haiti",
      "HM": "Heard Island And Mcdonald Islands",
      "VA": "Holy See (vatican City State)",
      "HN": "Honduras",
      "HK": "Hong Kong",
      "HU": "Hungary",
      "IS": "Iceland",
      "IN": "India",
      "ID": "Indonesia",
      "IR": "Iran, Islamic Republic Of",
      "IQ": "Iraq",
      "IE": "Ireland",
      "IM": "Isle Of Man",
      "IL": "Israel",
      "IT": "Italy",
      "JM": "Jamaica",
      "JP": "Japan",
      "JE": "Jersey",
      "JO": "Jordan",
      "KZ": "Kazakhstan",
      "KE": "Kenya",
      "KI": "Kiribati",
      "KP": "Korea, Democratic People's Republic Of",
      "KR": "Korea, Republic Of",
      "KW": "Kuwait",
      "KG": "Kyrgyzstan",
      "LA": "Lao People's Democratic Republic",
      "LV": "Latvia",
      "LB": "Lebanon",
      "LS": "Lesotho",
      "LR": "Liberia",
      "LY": "Libyan Arab Jamahiriya",
      "LI": "Liechtenstein",
      "LT": "Lithuania",
      "LU": "Luxembourg",
      "MO": "Macao",
      "MK": "Macedonia, The Former Yugoslav Republic Of",
      "MG": "Madagascar",
      "MW": "Malawi",
      "MY": "Malaysia",
      "MV": "Maldives",
      "ML": "Mali",
      "MT": "Malta",
      "MH": "Marshall Islands",
      "MQ": "Martinique",
      "MR": "Mauritania",
      "MU": "Mauritius",
      "YT": "Mayotte",
      "MX": "Mexico",
      "FM": "Micronesia, Federated States Of",
      "MD": "Moldova, Republic Of",
      "MC": "Monaco",
      "MN": "Mongolia",
      "ME": "Montenegro",
      "MS": "Montserrat",
      "MA": "Morocco",
      "MZ": "Mozambique",
      "MM": "Myanmar",
      "NA": "Namibia",
      "NR": "Nauru",
      "NP": "Nepal",
      "NL": "Netherlands",
      "AN": "Netherlands Antilles",
      "NC": "New Caledonia",
      "NZ": "New Zealand",
      "NI": "Nicaragua",
      "NE": "Niger",
      "NG": "Nigeria",
      "NU": "Niue",
      "NF": "Norfolk Island",
      "MP": "Northern Mariana Islands",
      "NO": "Norway",
      "OM": "Oman",
      "PK": "Pakistan",
      "PW": "Palau",
      "PS": "Palestinian Territory, Occupied",
      "PA": "Panama",
      "PG": "Papua New Guinea",
      "PY": "Paraguay",
      "PE": "Peru",
      "PH": "Philippines",
      "PN": "Pitcairn",
      "PL": "Poland",
      "PT": "Portugal",
      "PR": "Puerto Rico",
      "QA": "Qatar",
      "RE": "Réunion",
      "RO": "Romania",
      "RU": "Russian Federation",
      "RW": "Rwanda",
      "BL": "Saint Barthélemy",
      "SH": "Saint Helena, Ascension And Tristan Da Cunha",
      "KN": "Saint Kitts And Nevis",
      "LC": "Saint Lucia",
      "MF": "Saint Martin (french Part)",
      "PM": "Saint Pierre And Miquelon",
      "VC": "Saint Vincent And The Grenadines",
      "WS": "Samoa",
      "SM": "San Marino",
      "ST": "Sao Tome And Principe",
      "SA": "Saudi Arabia",
      "SN": "Senegal",
      "RS": "Serbia",
      "SC": "Seychelles",
      "SL": "Sierra Leone",
      "SG": "Singapore",
      "SK": "Slovakia",
      "SI": "Slovenia",
      "SB": "Solomon Islands",
      "SO": "Somalia",
      "ZA": "South Africa",
      "GS": "South Georgia And The South Sandwich Islands",
      "ES": "Spain",
      "LK": "Sri Lanka",
      "SD": "Sudan",
      "SR": "Suriname",
      "SJ": "Svalbard And Jan Mayen",
      "SZ": "Swaziland",
      "SE": "Sweden",
      "CH": "Switzerland",
      "SY": "Syrian Arab Republic",
      "TW": "Taiwan, Province Of China",
      "TJ": "Tajikistan",
      "TZ": "Tanzania, United Republic Of",
      "TH": "Thailand",
      "TL": "Timor-leste",
      "TG": "Togo",
      "TK": "Tokelau",
      "TO": "Tonga",
      "TT": "Trinidad And Tobago",
      "TN": "Tunisia",
      "TR": "Turkey",
      "TM": "Turkmenistan",
      "TC": "Turks And Caicos Islands",
      "TV": "Tuvalu",
      "UG": "Uganda",
      "UA": "Ukraine",
      "AE": "United Arab Emirates",
      "GB": "United Kingdom",
      "US": "United States",
      "UM": "United States Minor Outlying Islands",
      "UY": "Uruguay",
      "UZ": "Uzbekistan",
      "VU": "Vanuatu",
      "VE": "Venezuela, Bolivarian Republic Of",
      "VN": "Viet Nam",
      "VG": "Virgin Islands, British",
      "VI": "Virgin Islands, U.s.",
      "WF": "Wallis And Futuna",
      "EH": "Western Sahara",
      "YE": "Yemen",
      "ZM": "Zambia",
      "ZW": "Zimbabwe"
    },
    "by_alpha3": {
      "AFG": "Afghanistan",
      "ALA": "Åland Islands",
      "ALB": "Albania",
      "DZA": "Algeria",
      "ASM": "American Samoa",
      "AND": "Andorra",
      "AGO": "Angola",
      "AIA": "Anguilla",
      "ATA": "Antarctica",
      "ATG": "Antigua And Barbuda",
      "ARG": "Argentina",
      "ARM": "Armenia",
      "ABW": "Aruba",
      "AUS": "Australia",
      "AUT": "Austria",
      "AZE": "Azerbaijan",
      "BHS": "Bahamas",
      "BHR": "Bahrain",
      "BGD": "Bangladesh",
      "BRB": "Barbados",
      "BLR": "Belarus",
      "BEL": "Belgium",
      "BLZ": "Belize",
      "BEN": "Benin",
      "BMU": "Bermuda",
      "BTN": "Bhutan",
      "BOL": "Bolivia, Plurinational State Of",
      "BIH": "Bosnia And Herzegovina",
      "BWA": "Botswana",
      "BVT": "Bouvet Island",
      "BRA": "Brazil",
      "IOT": "British Indian Ocean Territory",
      "BRN": "Brunei Darussalam",
      "BGR": "Bulgaria",
      "BFA": "Burkina Faso",
      "BDI": "Burundi",
      "KHM": "Cambodia",
      "CMR": "Cameroon",
      "CAN": "Canada",
      "CPV": "Cape Verde",
      "CYM": "Cayman Islands",
      "CAF": "Central African Republic",
      "TCD": "Chad",
      "CHL": "Chile",
      "CHN": "China",
      "CXR": "Christmas Island",
      "CCK": "Cocos (keeling) Islands",
      "COL": "Colombia",
      "COM": "Comoros",
      "COG": "Congo",
      "COD": "Congo, The Democratic Republic Of The",
      "COK": "Cook Islands",
      "CRI": "Costa Rica",
      "CIV": "Côte D'ivoire",
      "HRV": "Croatia",
      "CUB": "Cuba",
      "CYP": "Cyprus",
      "CZE": "Czech Republic",
      "DNK": "Denmark",
      "DJI": "Djibouti",
      "DMA": "Dominica",
      "DOM": "Dominican Republic",
      "ECU": "Ecuador",
      "EGY": "Egypt",
      "SLV": "El Salvador",
      "GNQ": "Equatorial Guinea",
      "ERI": "Eritrea",
      "EST": "Estonia",
      "ETH": "Ethiopia",
      "FLK": "Falkland Islands (malvinas)",
      "FRO": "Faroe Islands",
      "FJI": "Fiji",
      "FIN": "Finland",
      "FRA": "France",
      "GUF": "French Guiana",
      "PYF": "French Polynesia",
      "ATF": "French Southern Territories",
      "GAB": "Gabon",
      "GMB": "Gambia",
      "GEO": "Georgia",
      "DEU": "Germany",
      "GHA": "Ghana",
      "GIB": "Gibraltar",
      "GRC": "Greece",
      "GRL": "Greenland",
      "GRD": "Grenada",
      "GLP": "Guadeloupe",
      "GUM": "Guam",
      "GTM": "Guatemala",
      "GGY": "Guernsey",
      "GIN": "Guinea",
      "GNB": "Guinea-bissau",
      "GUY": "Guyana",
      "HTI": "Haiti",
      "HMD": "Heard Island And Mcdonald Islands",
      "VAT": "Holy See (vatican City State)",
      "HND": "Honduras",
      "HKG": "Hong Kong",
      "HUN": "Hungary",
      "ISL": "Iceland",
      "IND": "India",
      "IDN": "Indonesia",
      "IRN": "Iran, Islamic Republic Of",
      "IRQ": "Iraq",
      "IRL": "Ireland",
      "IMN": "Isle Of Man",
      "ISR": "Israel",
      "ITA": "Italy",
      "JAM": "Jamaica",
      "JPN": "Japan",
      "JEY": "Jersey",
      "JOR": "Jordan",
      "KAZ": "Kazakhstan",
      "KEN": "Kenya",
      "KIR": "Kiribati",
      "PRK": "Korea, Democratic People's Republic Of",
      "KOR": "Korea, Republic Of",
      "KWT": "Kuwait",
      "KGZ": "Kyrgyzstan",
      "LAO": "Lao People's Democratic Republic",
      "LVA": "Latvia",
      "LBN": "Lebanon",
      "LSO": "Lesotho",
      "LBR": "Liberia",
      "LBY": "Libyan Arab Jamahiriya",
      "LIE": "Liechtenstein",
      "LTU": "Lithuania",
      "LUX": "Luxembourg",
      "MAC": "Macao",
      "MKD": "Macedonia, The Former Yugoslav Republic Of",
      "MDG": "Madagascar",
      "MWI": "Malawi",
      "MYS": "Malaysia",
      "MDV": "Maldives",
      "MLI": "Mali",
      "MLT": "Malta",
      "MHL": "Marshall Islands",
      "MTQ": "Martinique",
      "MRT": "Mauritania",
      "MUS": "Mauritius",
      "MYT": "Mayotte",
      "MEX": "Mexico",
      "FSM": "Micronesia, Federated States Of",
      "MDA": "Moldova, Republic Of",
      "MCO": "Monaco",
      "MNG": "Mongolia",
      "MNE": "Montenegro",
      "MSR": "Montserrat",
      "MAR": "Morocco",
      "MOZ": "Mozambique",
      "MMR": "Myanmar",
      "NAM": "Namibia",
      "NRU": "Nauru",
      "NPL": "Nepal",
      "NLD": "Netherlands",
      "ANT": "Netherlands Antilles",
      "NCL": "New Caledonia",
      "NZL": "New Zealand",
      "NIC": "Nicaragua",
      "NER": "Niger",
      "NGA": "Nigeria",
      "NIU": "Niue",
      "NFK": "Norfolk Island",
      "MNP": "Northern Mariana Islands",
      "NOR": "Norway",
      "OMN": "Oman",
      "PAK": "Pakistan",
      "PLW": "Palau",
      "PSE": "Palestinian Territory, Occupied",
      "PAN": "Panama",
      "PNG": "Papua New Guinea",
      "PRY": "Paraguay",
      "PER": "Peru",
      "PHL": "Philippines",
      "PCN": "Pitcairn",
      "POL": "Poland",
      "PRT": "Portugal",
      "PRI": "Puerto Rico",
      "QAT": "Qatar",
      "REU": "Réunion",
      "ROU": "Romania",
      "RUS": "Russian Federation",
      "RWA": "Rwanda",
      "BLM": "Saint Barthélemy",
      "SHN": "Saint Helena, Ascension And Tristan Da Cunha",
      "KNA": "Saint Kitts And Nevis",
      "LCA": "Saint Lucia",
      "MAF": "Saint Martin (french Part)",
      "SPM": "Saint Pierre And Miquelon",
      "VCT": "Saint Vincent And The Grenadines",
      "WSM": "Samoa",
      "SMR": "San Marino",
      "STP": "Sao Tome And Principe",
      "SAU": "Saudi Arabia",
      "SEN": "Senegal",
      "SRB": "Serbia",
      "SYC": "Seychelles",
      "SLE": "Sierra Leone",
      "SGP": "Singapore",
      "SVK": "Slovakia",
      "SVN": "Slovenia",
      "SLB": "Solomon Islands",
      "SOM": "Somalia",
      "ZAF": "South Africa",
      "SGS": "South Georgia And The South Sandwich Islands",
      "ESP": "Spain",
      "LKA": "Sri Lanka",
      "SDN": "Sudan",
      "SUR": "Suriname",
      "SJM": "Svalbard And Jan Mayen",
      "SWZ": "Swaziland",
      "SWE": "Sweden",
      "CHE": "Switzerland",
      "SYR": "Syrian Arab Republic",
      "TWN": "Taiwan, Province Of China",
      "TJK": "Tajikistan",
      "TZA": "Tanzania, United Republic Of",
      "THA": "Thailand",
      "TLS": "Timor-leste",
      "TGO": "Togo",
      "TKL": "Tokelau",
      "TON": "Tonga",
      "TTO": "Trinidad And Tobago",
      "TUN": "Tunisia",
      "TUR": "Turkey",
      "TKM": "Turkmenistan",
      "TCA": "Turks And Caicos Islands",
      "TUV": "Tuvalu",
      "UGA": "Uganda",
      "UKR": "Ukraine",
      "ARE": "United Arab Emirates",
      "GBR": "United Kingdom",
      "USA": "United States",
      "UMI": "United States Minor Outlying Islands",
      "URY": "Uruguay",
      "UZB": "Uzbekistan",
      "VUT": "Vanuatu",
      "VEN": "Venezuela, Bolivarian Republic Of",
      "VNM": "Viet Nam",
      "VGB": "Virgin Islands, British",
      "VIR": "Virgin Islands, U.s.",
      "WLF": "Wallis And Futuna",
      "ESH": "Western Sahara",
      "YEM": "Yemen",
      "ZMB": "Zambia",
      "ZWE": "Zimbabwe"
    },
    "by_name": {
      "AFGHANISTAN": "Afghanistan",
      "LAND ISLANDS": "Åland Islands",
      "ALBANIA": "Albania",
      "ALGERIA": "Algeria",
      "AMERICAN SAMOA": "American Samoa",
      "ANDORRA": "Andorra",
      "ANGOLA": "Angola",
      "ANGUILLA": "Anguilla",
      "ANTARCTICA": "Antarctica",
      "ANTIGUA AND BARBUDA": "Antigua And Barbuda",
      "ARGENTINA": "Argentina",
      "ARMENIA": "Armenia",
      "ARUBA": "Aruba",
      "AUSTRALIA": "Australia",
      "AUSTRIA": "Austria",
      "AZERBAIJAN": "Azerbaijan",
      "BAHAMAS": "Bahamas",
      "BAHRAIN": "Bahrain",
      "BANGLADESH": "Bangladesh",
      "BARBADOS": "Barbados",
      "BELARUS": "Belarus",
      "BELGIUM": "Belgium",
      "BELIZE": "Belize",
      "BENIN": "Benin",
      "BERMUDA": "Bermuda",
      "BHUTAN": "Bhutan",
      "BOLIVIA PLURINATIONAL STATE OF": "Bolivia, Plurinational State Of",
      "BOSNIA AND HERZEGOVINA": "Bosnia And Herzegovina",
      "BOTSWANA": "Botswana",
      "BOUVET ISLAND": "Bouvet Island",
      "BRAZIL": "Brazil",
      "BRITISH INDIAN OCEAN TERRITORY": "British Indian Ocean Territory",
      "BRUNEI DARUSSALAM": "Brunei Darussalam",
      "BULGARIA": "Bulgaria",
      "BURKINA FASO": "Burkina Faso",
      "BURUNDI": "Burundi",
      "CAMBODIA": "Cambodia",
      "CAMEROON": "Cameroon",
      "CANADA": "Canada",
      "CAPE VERDE": "Cape Verde",
      "CAYMAN ISLANDS": "Cayman Islands",
      "CENTRAL AFRICAN REPUBLIC": "Central African Republic",
      "CHAD": "Chad",
      "CHILE": "Chile",
      "CHINA": "China",
      "CHRISTMAS ISLAND": "Christmas Island",
      "COCOS KEELING ISLANDS": "Cocos (keeling) Islands",
      "COLOMBIA": "Colombia",
      "COMOROS": "Comoros",
      "CONGO": "Congo",
      "CONGO THE DEMOCRATIC REPUBLIC OF THE": "Congo, The Democratic Republic Of The",
      "COOK ISLANDS": "Cook Islands",
      "COSTA RICA": "Costa Rica",
      "C TE D IVOIRE": "Côte D'ivoire",
      "CROATIA": "Croatia",
      "CUBA": "Cuba",
      "CYPRUS": "Cyprus",
      "CZECH REPUBLIC": "Czech Republic",
      "DENMARK": "Denmark",
      "DJIBOUTI": "Djibouti",
      "DOMINICA": "Dominica",
      "DOMINICAN REPUBLIC": "Dominican Republic",
      "ECUADOR": "Ecuador",
      "EGYPT": "Egypt",
      "EL SALVADOR": "El Salvador",
      "EQUATORIAL GUINEA": "Equatorial Guinea",
      "ERITREA": "Eritrea",
      "ESTONIA": "Estonia",
      "ETHIOPIA": "Ethiopia",
      "FALKLAND ISLANDS MALVINAS": "Falkland Islands (malvinas)",
      "FAROE ISLANDS": "Faroe Islands",
      "FIJI": "Fiji",
      "FINLAND": "Finland",
      "FRANCE": "France",
      "FRENCH GUIANA": "French Guiana",
      "FRENCH POLYNESIA": "French Polynesia",
      "FRENCH SOUTHERN TERRITORIES": "French Southern Territories",
      "GABON": "Gabon",
      "GAMBIA": "Gambia",
      "GEORGIA": "Georgia",
      "GERMANY": "Germany",
      "GHANA": "Ghana",
      "GIBRALTAR": "Gibraltar",
      "GREECE": "Greece",
      "GREENLAND": "Greenland",
      "GRENADA": "Grenada",
      "GUADELOUPE": "Guadeloupe",
      "GUAM": "Guam",
      "GUATEMALA": "Guatemala",
      "GUERNSEY": "Guernsey",
      "GUINEA": "Guinea",
      "GUINEA BISSAU": "Guinea-bissau",
      "GUYANA": "Guyana",
      "HAITI": "Haiti",
      "HEARD ISLAND AND MCDONALD ISLANDS": "Heard Island And Mcdonald Islands",
      "HOLY SEE VATICAN CITY STATE": "Holy See (vatican City State)",
      "HONDURAS": "Honduras",
      "HONG KONG": "Hong Kong",
      "HUNGARY": "Hungary",
      "ICELAND": "Iceland",
      "INDIA": "India",
      "INDONESIA": "Indonesia",
      "IRAN ISLAMIC REPUBLIC OF": "Iran, Islamic Republic Of",
      "IRAQ": "Iraq",
      "IRELAND": "Ireland",
      "ISLE OF MAN": "Isle Of Man",
      "ISRAEL": "Israel",
      "ITALY": "Italy",
      "JAMAICA": "Jamaica",
      "JAPAN": "Japan",
      "JERSEY": "Jersey",
      "JORDAN": "Jordan",
      "KAZAKHSTAN": "Kazakhstan",
      "KENYA": "Kenya",
      "KIRIBATI": "Kiribati",
      "KOREA DEMOCRATIC PEOPLE S REPUBLIC OF": "Korea, Democratic People's Republic Of",
      "KOREA REPUBLIC OF": "Korea, Republic Of",
      "KUWAIT": "Kuwait",
      "KYRGYZSTAN": "Kyrgyzstan",
      "LAO PEOPLE S DEMOCRATIC REPUBLIC": "Lao People's Democratic Republic",
      "LATVIA": "Latvia",
      "LEBANON": "Lebanon",
      "LESOTHO": "Lesotho",
      "LIBERIA": "Liberia",
      "LIBYAN ARAB JAMAHIRIYA": "Libyan Arab Jamahiriya",
      "LIECHTENSTEIN": "Liechtenstein",
      "LITHUANIA": "Lithuania",
      "LUXEMBOURG": "Luxembourg",
      "MACAO": "Macao",
      "MACEDONIA THE FORMER YUGOSLAV REPUBLIC OF": "Macedonia, The Former Yugoslav Republic Of",
      "MADAGASCAR": "Madagascar",
      "MALAWI": "Malawi",
      "MALAYSIA": "Malaysia",
      "MALDIVES": "Maldives",
      "MALI": "Mali",
      "MALTA": "Malta",
      "MARSHALL ISLANDS": "Marshall Islands",
      "MARTINIQUE": "Martinique",
      "MAURITANIA": "Mauritania",
      "MAURITIUS": "Mauritius",
      "MAYOTTE": "Mayotte",
      "MEXICO": "Mexico",
      "MICRONESIA FEDERATED STATES OF": "Micronesia, Federated States Of",
      "MOLDOVA REPUBLIC OF": "Moldova, Republic Of",
      "MONACO": "Monaco",
      "MONGOLIA": "Mongolia",
      "MONTENEGRO": "Montenegro",
      "MONTSERRAT": "Montserrat",
      "MOROCCO": "Morocco",
      "MOZAMBIQUE": "Mozambique",
      "MYANMAR": "Myanmar",
      "NAMIBIA": "Namibia",
      "NAURU": "Nauru",
      "NEPAL": "Nepal",
      "NETHERLANDS": "Netherlands",
      "NETHERLANDS ANTILLES": "Netherlands Antilles",
      "NEW CALEDONIA": "New Caledonia",
      "NEW ZEALAND": "New Zealand",
      "NICARAGUA": "Nicaragua",
      "NIGER": "Niger",
      "NIGERIA": "Nigeria",
      "NIUE": "Niue",
      "NORFOLK ISLAND": "Norfolk Island",
      "NORTHERN MARIANA ISLANDS": "Northern Mariana Islands",
      "NORWAY": "Norway",
      "OMAN": "Oman",
      "PAKISTAN": "Pakistan",
      "PALAU": "Palau",
      "PALESTINIAN TERRITORY OCCUPIED": "Palestinian Territory, Occupied",
      "PANAMA": "Panama",
      "PAPUA NEW GUINEA": "Papua New Guinea",
      "PARAGUAY": "Paraguay",
      "PERU": "Peru",
      "PHILIPPINES": "Philippines",
      "PITCAIRN": "Pitcairn",
      "POLAND": "Poland",
      "PORTUGAL": "Portugal",
      "PUERTO RICO": "Puerto Rico",
      "QATAR": "Qatar",
      "R UNION": "Réunion",
      "ROMANIA": "Romania",
      "RUSSIAN FEDERATION": "Russian Federation",
      "RWANDA": "Rwanda",
      "SAINT BARTH LEMY": "Saint Barthélemy",
      "SAINT HELENA ASCENSION AND TRISTAN DA CUNHA": "Saint Helena, Ascension And Tristan Da Cunha",
      "SAINT KITTS AND NEVIS": "Saint Kitts And Nevis",
      "SAINT LUCIA": "Saint Lucia",
      "SAINT MARTIN FRENCH PART": "Saint Martin (french Part)",
      "SAINT PIERRE AND MIQUELON": "Saint Pierre And Miquelon",
      "SAINT VINCENT AND THE GRENADINES": "Saint Vincent And The Grenadines",
      "SAMOA": "Samoa",
      "SAN MARINO": "San Marino",
      "SAO TOME AND PRINCIPE": "Sao Tome And Principe",
      "SAUDI ARABIA": "Saudi Arabia",
      "SENEGAL": "Senegal",
      "SERBIA": "Serbia",
      "SEYCHELLES": "Seychelles",
      "SIERRA LEONE": "Sierra Leone",
      "SINGAPORE": "Singapore",
      "SLOVAKIA": "Slovakia",
      "SLOVENIA": "Slovenia",
      "SOLOMON ISLANDS": "Solomon Islands",
      "SOMALIA": "Somalia",
      "SOUTH AFRICA": "South Africa",
      "SOUTH GEORGIA AND THE SOUTH SANDWICH ISLANDS": "South Georgia And The South Sandwich Islands",
      "SPAIN": "Spain",
      "SRI LANKA": "Sri Lanka",
      "SUDAN": "Sudan",
      "SURINAME": "Suriname",
      "SVALBARD AND JAN MAYEN": "Svalbard And Jan Mayen",
      "SWAZILAND": "Swaziland",
      "SWEDEN": "Sweden",
      "SWITZERLAND": "Switzerland",
      "SYRIAN ARAB REPUBLIC": "Syrian Arab Republic",
      "TAIWAN PROVINCE OF CHINA": "Taiwan, Province Of China",
      "TAJIKISTAN": "Tajikistan",
      "TANZANIA UNITED REPUBLIC OF": "Tanzania, United Republic Of",
      "THAILAND": "Thailand",
      "TIMOR LESTE": "Timor-leste",
      "TOGO": "Togo",
      "TOKELAU": "Tokelau",
      "TONGA": "Tonga",
      "TRINIDAD AND TOBAGO": "Trinidad And Tobago",
      "TUNISIA": "Tunisia",
      "TURKEY": "Turkey",
      "TURKMENISTAN": "Turkmenistan",
      "TURKS AND CAICOS ISLANDS": "Turks And Caicos Islands",
      "TUVALU": "Tuvalu",
      "UGANDA": "Uganda",
      "UKRAINE": "Ukraine",
      "UNITED ARAB EMIRATES": "United Arab Emirates",
      "UNITED KINGDOM": "United Kingdom",
      "UNITED STATES": "United States",
      "UNITED STATES MINOR OUTLYING ISLANDS": "United States Minor Outlying Islands",
      "URUGUAY": "Uruguay",
      "UZBEKISTAN": "Uzbekistan",
      "VANUATU": "Vanuatu",
      "VENEZUELA BOLIVARIAN REPUBLIC OF": "Venezuela, Bolivarian Republic Of",
      "VIET NAM": "Viet Nam",
      "VIRGIN ISLANDS BRITISH": "Virgin Islands, British",
      "VIRGIN ISLANDS U S": "Virgin Islands, U.s.",
      "WALLIS AND FUTUNA": "Wallis And Futuna",
      "WESTERN SAHARA": "Western Sahara",
      "YEMEN": "Yemen",
      "ZAMBIA": "Zambia",
      "ZIMBABWE": "Zimbabwe"
    },
    "aliases": {
      "USA": "United States",
      "U S": "United States",
      "U S A": "United States",
      "UNITEDSTATES": "United States",
      "UNITED STATES OF AMERICA": "United States",
      "UK": "United Kingdom",
      "GREAT BRITAIN": "United Kingdom",
      "UNITEDKINGDOM": "United Kingdom",
      "UAE": "United Arab Emirates",
      "UNITEDARABEMIRATES": "United Arab Emirates",
      "VIETNAM": "Viet Nam",
      "ELSALVADOR": "El Salvador",
      "CZECHIA": "Czech Republic",
      "KOREA": "Korea, Republic Of",
      "SOUTHKOREA": "Korea, Republic Of",
      "NORTHKOREA": "Korea, Democratic People's Republic Of",
      "SOUTHAFRICA": "South Africa",
      "SOUTHSUDAN": "South Sudan",
      "NEWZEALAND": "New Zealand",
      "COSTARICA": "Costa Rica",
      "SAUDIARABIA": "Saudi Arabia",
      "SRILANKA": "Sri Lanka",
      "HONGKONG": "Hong Kong",
      "PAPUANEWGUINEA": "Papua New Guinea",
      "SANMARINO": "San Marino",
      "SIERRALEONE": "Sierra Leone",
      "BOSNIAHERZEGOVINA": "Bosnia And Herzegovina",
      "GUINEABISSAU": "Guinea-bissau",
      "TIMORLESTE": "Timor-leste",
      "CAPEVERDE": "Cape Verde",
      "FAROEISLANDS": "Faroe Islands",
      "NORFOLKISLAND": "Norfolk Island",
      "NORTHERNMARIANAISLANDS": "Northern Mariana Islands",
      "PUERTORICO": "Puerto Rico",
      "DOMINICANREPUBLIC": "Dominican Republic",
      "EQUATORIALGUINEA": "Equatorial Guinea",
      "CENTRALAFRICANREPUBLIC": "Central African Republic",
      "SOLOMONISLANDS": "Solomon Islands",
      "COOKISLANDS": "Cook Islands",
      "MARSHALLISLANDS": "Marshall Islands",
      "CAYMANISLANDS": "Cayman Islands",
      "FALKLANDISLANDS": "Falkland Islands (malvinas)",
      "TURKSANDCAICOSISLANDS": "Turks And Caicos Islands",
      "BRITISHVIRGINISLANDS": "Virgin Islands, British",
      "USVIRGINISLANDS": "Virgin Islands, U.s.",
      "MACAU": "Macao",
      "MACEDONIA": "Macedonia, The Former Yugoslav Republic Of",
      "PALESTINE": "Palestinian Territory, Occupied",
      "LAOS": "Lao People's Democratic Republic",
      "MOLDOVA": "Moldova, Republic Of",
      "RUSSIA": "Russian Federation",
      "BOLIVIA": "Bolivia, Plurinational State Of",
      "VENEZUELA": "Venezuela, Bolivarian Republic Of",
      "TAIWAN": "Taiwan, Province Of China",
      "SYRIA": "Syrian Arab Republic",
      "IRAN": "Iran, Islamic Republic Of",
      "TANZANIA": "Tanzania, United Republic Of",
      "BRUNEI": "Brunei Darussalam",
      "MICRONESIA": "Micronesia, Federated States Of"
    }
  },
  "us_states": {
    "by_abbreviation": {
      "AL": "Alabama",
      "AK": "Alaska",
      "AZ": "Arizona",
      "AR": "Arkansas",
      "CA": "California",
      "CO": "Colorado",
      "CT": "Connecticut",
      "DE": "Delaware",
      "DC": "District Of Columbia",
      "FL": "Florida",
      "GA": "Georgia",
      "HI": "Hawaii",
      "ID": "Idaho",
      "IL": "Illinois",
      "IN": "Indiana",
      "IA": "Iowa",
      "KS": "Kansas",
      "KY": "Kentucky",
      "LA": "Louisiana",
      "ME": "Maine",
      "MT": "Montana",
      "NE": "Nebraska",
      "NV": "Nevada",
      "NH": "New Hampshire",
      "NJ": "New Jersey",
      "NM": "New Mexico",
      "NY": "New York",
      "NC": "North Carolina",
      "ND": "North Dakota",
      "OH": "Ohio",
      "OK": "Oklahoma",
      "OR": "Oregon",
      "MD": "Maryland",
      "MA": "Massachusetts",
      "MI": "Michigan",
      "MN": "Minnesota",
      "MS": "Mississippi",
      "MO": "Missouri",
      "PA": "Pennsylvania",
      "RI": "Rhode Island",
      "SC": "South Carolina",
      "SD": "South Dakota",
      "TN": "Tennessee",
      "TX": "Texas",
      "UT": "Utah",
      "VT": "Vermont",
      "VA": "Virginia",
      "WA": "Washington",
      "WV": "West Virginia",
      "WI": "Wisconsin",
      "WY": "Wyoming"
    },
    "by_name": {
      "ALABAMA": "Alabama",
      "ALASKA": "Alaska",
      "ARIZONA": "Arizona",
      "ARKANSAS": "Arkansas",
      "CALIFORNIA": "California",
      "COLORADO": "Colorado",
      "CONNECTICUT": "Connecticut",
      "DELAWARE": "Delaware",
      "DISTRICT OF COLUMBIA": "District Of Columbia",
      "FLORIDA": "Florida",
      "GEORGIA": "Georgia",
      "HAWAII": "Hawaii",
      "IDAHO": "Idaho",
      "ILLINOIS": "Illinois",
      "INDIANA": "Indiana",
      "IOWA": "Iowa",
      "KANSAS": "Kansas",
      "KENTUCKY": "Kentucky",
      "LOUISIANA": "Louisiana",
      "MAINE": "Maine",
      "MONTANA": "Montana",
      "NEBRASKA": "Nebraska",
      "NEVADA": "Nevada",
      "NEW HAMPSHIRE": "New Hampshire",
      "NEW JERSEY": "New Jersey",
      "NEW MEXICO": "New Mexico",
      "NEW YORK": "New York",
      "NORTH CAROLINA": "North Carolina",
      "NORTH DAKOTA": "North Dakota",
      "OHIO": "Ohio",
      "OKLAHOMA": "Oklahoma",
      "OREGON": "Oregon",
      "MARYLAND": "Maryland",
      "MASSACHUSETTS": "Massachusetts",
      "MICHIGAN": "Michigan",
      "MINNESOTA": "Minnesota",
      "MISSISSIPPI": "Mississippi",
      "MISSOURI": "Missouri",
      "PENNSYLVANIA": "Pennsylvania",
      "RHODE ISLAND": "Rhode Island",
      "SOUTH CAROLINA": "South Carolina",
      "SOUTH DAKOTA": "South Dakota",
      "TENNESSEE": "Tennessee",
      "TEXAS": "Texas",
      "UTAH": "Utah",
      "VERMONT": "Vermont",
      "VIRGINIA": "Virginia",
      "WASHINGTON": "Washington",
      "WEST VIRGINIA": "West Virginia",
      "WISCONSIN": "Wisconsin",
      "WYOMING": "Wyoming"
    }
  },
  "regions": {
    "by_name": {
      "AFRICA": ["Algeria", "Angola", "Benin", "Botswana", "Burkina Faso", "Burundi", "Cabo Verde", "Cameroon", "Central African Republic", "Chad", "Comoros", "Congo", "Democratic Republic of the Congo", "Djibouti", "Egypt", "Equatorial Guinea", "Eritrea", "Eswatini", "Ethiopia", "Gabon", "Gambia", "Ghana", "Guinea", "Guinea-Bissau", "Ivory Coast", "Kenya", "Lesotho", "Liberia", "Libya", "Madagascar", "Malawi", "Mali", "Mauritania", "Mauritius", "Morocco", "Mozambique", "Namibia", "Niger", "Nigeria", "Rwanda", "Sao Tome and Principe", "Senegal", "Seychelles", "Sierra Leone", "Somalia", "South Africa", "South Sudan", "Sudan", "Tanzania", "Togo", "Tunisia", "Uganda", "Zambia", "Zimbabwe"],
      "ASIA": ["Afghanistan", "Armenia", "Azerbaijan", "Bahrain", "Bangladesh", "Bhutan", "Brunei", "Cambodia", "China", "Cyprus", "Georgia", "India", "Indonesia", "Iran", "Iraq", "Israel", "Japan", "Jordan", "Kazakhstan", "Kuwait", "Kyrgyzstan", "Laos", "Lebanon", "Malaysia", "Maldives", "Mongolia", "Myanmar", "Nepal", "North Korea", "Oman", "Pakistan", "Palestine", "Philippines", "Qatar", "Saudi Arabia", "Singapore", "South Korea", "Sri Lanka", "Syria", "Taiwan", "Tajikistan", "Thailand", "Timor-Leste", "Turkey", "Turkmenistan", "United Arab Emirates", "Uzbekistan", "Vietnam", "Yemen"],
      "ASIA PACIFIC": ["Afghanistan", "Armenia", "Australia", "Azerbaijan", "Bahrain", "Bangladesh", "Bhutan", "Brunei", "Cambodia", "China", "Cyprus", "Fiji", "Georgia", "India", "Indonesia", "Iran", "Iraq", "Israel", "Japan", "Jordan", "Kazakhstan", "Kiribati", "Kuwait", "Kyrgyzstan", "Laos", "Lebanon", "Malaysia", "Maldives", "Marshall Islands", "Micronesia", "Mongolia", "Myanmar", "Nauru", "Nepal", "New Zealand", "North Korea", "Oman", "Pakistan", "Palau", "Palestine", "Papua New Guinea", "Philippines", "Qatar", "Samoa", "Saudi Arabia", "Singapore", "Solomon Islands", "South Korea", "Sri Lanka", "Syria", "Taiwan", "Tajikistan", "Thailand", "Timor-Leste", "Tonga", "Turkey", "Turkmenistan", "Tuvalu", "United Arab Emirates", "Uzbekistan", "Vanuatu", "Vietnam", "Yemen"],
      "CARIBBEAN": ["Antigua and Barbuda", "Bahamas", "Barbados", "Cuba", "Dominica", "Dominican Republic", "Grenada", "Haiti", "Jamaica", "Saint Kitts and Nevis", "Saint Lucia", "Saint Vincent and the Grenadines", "Trinidad and Tobago"],
      "CENTRAL AMERICA": ["Belize", "Costa Rica", "El Salvador", "Guatemala", "Honduras", "Nicaragua", "Panama"],
      "EMEA": ["Albania", "Algeria", "Andorra", "Angola", "Armenia", "Austria", "Azerbaijan", "Bahrain", "Belarus", "Belgium", "Benin", "Bosnia and Herzegovina", "Botswana", "Bulgaria", "Burkina Faso", "Burundi", "Cabo Verde", "Cameroon", "Central African Republic", "Chad", "Comoros", "Congo", "Croatia", "Cyprus", "Czechia", "Democratic Republic of the Congo", "Denmark", "Djibouti", "Egypt", "Equatorial Guinea", "Eritrea", "Estonia", "Eswatini", "Ethiopia", "Finland", "France", "Gabon", "Gambia", "Georgia", "Germany", "Ghana", "Greece", "Guinea", "Guinea-Bissau", "Hungary", "Iceland", "Iran", "Iraq", "Ireland", "Israel", "Italy", "Ivory Coast", "Jordan", "Kazakhstan", "Kenya", "Kosovo", "Kuwait", "Kyrgyzstan", "Laos", "Latvia", "Lebanon", "Lesotho", "Liberia", "Libya", "Liechtenstein", "Lithuania", "Luxembourg", "Madagascar", "Malawi", "Mali", "Malta", "Mauritania", "Mauritius", "Moldova", "Monaco", "Montenegro", "Morocco", "Mozambique", "Namibia", "Netherlands", "Niger", "Nigeria", "North Macedonia", "Norway", "Oman", "Palestine", "Poland", "Portugal", "Qatar", "Romania", "Russia", "Rwanda", "San Marino", "Sao Tome and Principe", "Saudi Arabia", "Senegal", "Serbia", "Seychelles", "Sierra Leone", "Slovakia", "Slovenia", "Somalia", "South Africa", "South Sudan", "Spain", "Sudan", "Sweden", "Switzerland", "Syria", "Tajikistan", "Tanzania", "Togo", "Tunisia", "Turkey", "Turkmenistan", "Uganda", "Ukraine", "United Arab Emirates", "United Kingdom", "Uzbekistan", "Vatican City", "Yemen", "Zambia", "Zimbabwe"],
      "EUROPE": ["Albania", "Andorra", "Austria", "Belarus", "Belgium", "Bosnia and Herzegovina", "Bulgaria", "Croatia", "Czechia", "Denmark", "Estonia", "Finland", "France", "Germany", "Greece", "Hungary", "Iceland", "Ireland", "Italy", "Kosovo", "Latvia", "Liechtenstein", "Lithuania", "Luxembourg", "Malta", "Moldova", "Monaco", "Montenegro", "Netherlands", "North Macedonia", "Norway", "Poland", "Portugal", "Romania", "Russia", "San Marino", "Serbia", "Slovakia", "Slovenia", "Spain", "Sweden", "Switzerland", "Ukraine", "United Kingdom", "Vatican City"],
      "LATIN AMERICA": ["Argentina", "Belize", "Bolivia", "Brazil", "Chile", "Colombia", "Costa Rica", "Cuba", "Dominican Republic", "Ecuador", "El Salvador", "Guatemala", "Honduras", "Mexico", "Nicaragua", "Panama", "Paraguay", "Peru", "Uruguay", "Venezuela"],
      "MIDDLE EAST": ["Bahrain", "Cyprus", "Egypt", "Iran", "Iraq", "Israel", "Jordan", "Kuwait", "Lebanon", "Oman", "Palestine", "Qatar", "Saudi Arabia", "Syria", "Turkey", "United Arab Emirates", "Yemen"],
      "NORTH AMERICA": ["Antigua and Barbuda", "Bahamas", "Barbados", "Belize", "Canada", "Costa Rica", "Cuba", "Dominica", "Dominican Republic", "El Salvador", "Grenada", "Guatemala", "Haiti", "Honduras", "Jamaica", "Mexico", "Nicaragua", "Panama", "Saint Kitts and Nevis", "Saint Lucia", "Saint Vincent and the Grenadines", "Trinidad and Tobago", "United States"],
      "OCEANIA": ["Australia", "Fiji", "Kiribati", "Marshall Islands", "Micronesia", "Nauru", "New Zealand", "Palau", "Papua New Guinea", "Samoa", "Solomon Islands", "Tonga", "Tuvalu", "Vanuatu"],
      "SOUTH AMERICA": ["Argentina", "Bolivia", "Brazil", "Chile", "Colombia", "Ecuador", "Guyana", "Paraguay", "Peru", "Suriname", "Uruguay", "Venezuela"],
      "AMERICAS": ["Antigua and Barbuda", "Argentina", "Bahamas", "Barbados", "Belize", "Bolivia", "Brazil", "Canada", "Chile", "Colombia", "Costa Rica", "Cuba", "Dominica", "Dominican Republic", "Ecuador", "El Salvador", "Grenada", "Guatemala", "Guyana", "Haiti", "Honduras", "Jamaica", "Mexico", "Nicaragua", "Panama", "Paraguay", "Peru", "Saint Kitts and Nevis", "Saint Lucia", "Saint Vincent and the Grenadines", "Suriname", "Trinidad and Tobago", "United States", "Uruguay", "Venezuela"],
      "USA TIMEZONES": ["United States"]
    },
    "aliases": {
      "AFRICA REGION": "AFRICA",
      "AMER": "AMERICAS",
      "AMERICA": "AMERICAS",
      "ANYWHERE": "WORLDWIDE",
      "APAC": "ASIA PACIFIC",
      "ASIA-PACIFIC": "ASIA PACIFIC",
      "ASIA PAC": "ASIA PACIFIC",
      "CARIBBEAN REGION": "CARIBBEAN",
      "CENTRAL AMERICA REGION": "CENTRAL AMERICA",
      "EMEA REGION": "EMEA",
      "EU": "EUROPE",
      "EUROPEAN UNION": "EUROPE",
      "GLOBAL": "WORLDWIDE",
      "GLOBALLY": "WORLDWIDE",
      "INTERNATIONAL": "WORLDWIDE",
      "LATAM": "LATIN AMERICA",
      "LATINAMERICA": "LATIN AMERICA",
      "MENA": "MIDDLE EAST",
      "MIDDLE EAST AND NORTH AFRICA": "EMEA",
      "NA": "NORTH AMERICA",
      "NORTHAMERICA": "NORTH AMERICA",
      "OCEANIA REGION": "OCEANIA",
      "REMOTE WORLDWIDE": "WORLDWIDE",
      "SOUTHAMERICA": "SOUTH AMERICA",
      "US TIMEZONES": "USA TIMEZONES",
      "US TIME ZONES": "USA TIMEZONES",
      "USA TIME ZONES": "USA TIMEZONES",
      "UNITED STATES TIMEZONES": "USA TIMEZONES",
      "UNITED STATES TIME ZONES": "USA TIMEZONES",
      "WORLD": "WORLDWIDE",
      "WORLDWIDE REMOTE": "WORLDWIDE",
      "WW": "WORLDWIDE"
    }
  }
}
